<response>
    <header>
        <resultCode>00</resultCode>
        <resultMsg>NORMAL_CODE</resultMsg>
    </header>
    <body>
        <items>
            <item>
                <afos_fid>6517752</afos_fid>
                <afos_id>2019038</afos_id>
                <bjd_cd>1159010700</bjd_cd>
                <spot_cd>11590001</spot_cd>
                <sido_sgg_nm>서울특별시 동작구1</sido_sgg_nm>
                <spot_nm>서울특별시 동작구 사당동(파리바게뜨 이수역자이점 부근)</spot_nm>
                <occrrnc_cnt>8</occrrnc_cnt>
                <caslt_cnt>8</caslt_cnt>
                <dth_dnv_cnt>0</dth_dnv_cnt>
                <se_dnv_cnt>1</se_dnv_cnt>
                <sl_dnv_cnt>3</sl_dnv_cnt>
                <wnd_dnv_cnt>4</wnd_dnv_cnt>
                <geom_json>{"type":"Polygon","coordinates":[[[126.98233269,37.48478252],[126.98229817,37.48450439],[126.98219593,37.48423694],[126.9820299,37.48399046],[126.98180647,37.48377442],[126.98153421,37.48359712],[126.9812236,37.48346537],[126.98088657,37.48338425],[126.98053606,37.48335685],[126.98018555,37.48338425],[126.97984852,37.48346537],[126.97953791,37.48359712],[126.97926565,37.48377442],[126.97904222,37.48399046],[126.97887619,37.48423694],[126.97877395,37.48450439],[126.97873943,37.48478252],[126.97877395,37.48506065],[126.97887619,37.48532809],[126.97904222,37.48557456],[126.97926565,37.4857906],[126.97953791,37.4859679],[126.97984852,37.48609964],[126.98018555,37.48618077],[126.98053606,37.48620816],[126.98088657,37.48618077],[126.9812236,37.48609964],[126.98153421,37.4859679],[126.98180647,37.4857906],[126.9820299,37.48557456],[126.98219593,37.48532809],[126.98229817,37.48506065],[126.98233269,37.48478252]]]}</geom_json>
                <lo_crd>126.980536060092</lo_crd>
                <la_crd>37.484782518399</la_crd>
            </item>
            <item>
                <afos_fid>6517751</afos_fid>
                <afos_id>2019038</afos_id>
                <bjd_cd>1159010400</bjd_cd>
                <spot_cd>11590002</spot_cd>
                <sido_sgg_nm>서울특별시 동작구2</sido_sgg_nm>
                <spot_nm>서울특별시 동작구 본동(한강대교남단교차로 부근)</spot_nm>
                <occrrnc_cnt>7</occrrnc_cnt>
                <caslt_cnt>7</caslt_cnt>
                <dth_dnv_cnt>0</dth_dnv_cnt>
                <se_dnv_cnt>2</se_dnv_cnt>
                <sl_dnv_cnt>3</sl_dnv_cnt>
                <wnd_dnv_cnt>2</wnd_dnv_cnt>
                <geom_json>{"type":"Polygon","coordinates":[[[126.95778274,37.51385747],[126.95774822,37.51357944],[126.95764598,37.5133121],[126.95747995,37.51306572],[126.95725652,37.51284976],[126.95698426,37.51267253],[126.95667365,37.51254084],[126.95633661,37.51245974],[126.95598611,37.51243236],[126.9556356,37.51245974],[126.95529857,37.51254084],[126.95498795,37.51267253],[126.9547157,37.51284976],[126.95449226,37.51306572],[126.95432624,37.5133121],[126.954224,37.51357944],[126.95418948,37.51385747],[126.954224,37.51413549],[126.95432624,37.51440283],[126.95449226,37.51464921],[126.9547157,37.51486516],[126.95498795,37.51504238],[126.95529857,37.51517408],[126.9556356,37.51525517],[126.95598611,37.51528255],[126.95633661,37.51525517],[126.95667365,37.51517408],[126.95698426,37.51504238],[126.95725652,37.51486516],[126.95747995,37.51464921],[126.95764598,37.51440283],[126.95774822,37.51413549],[126.95778274,37.51385747]]]}</geom_json>
                <lo_crd>126.955986107874</lo_crd>
                <la_crd>37.513857467949</la_crd>
            </item>
            <item>
                <afos_fid>6517749</afos_fid>
                <afos_id>2019038</afos_id>
                <bjd_cd>1159010900</bjd_cd>
                <spot_cd>11590003</spot_cd>
                <sido_sgg_nm>서울특별시 동작구3</sido_sgg_nm>
                <spot_nm>서울특별시 동작구 신대방동(대림사거리 부근)</spot_nm>
                <occrrnc_cnt>6</occrrnc_cnt>
                <caslt_cnt>6</caslt_cnt>
                <dth_dnv_cnt>0</dth_dnv_cnt>
                <se_dnv_cnt>1</se_dnv_cnt>
                <sl_dnv_cnt>4</sl_dnv_cnt>
                <wnd_dnv_cnt>1</wnd_dnv_cnt>
                <geom_json>{"type":"Polygon","coordinates":[[[126.90820169,37.48902893],[126.90816716,37.48875081],[126.90806492,37.48848338],[126.9078989,37.48823692],[126.90767546,37.48802089],[126.90740321,37.4878436],[126.9070926,37.48771186],[126.90675556,37.48763074],[126.90640505,37.48760334],[126.90605455,37.48763074],[126.90571751,37.48771186],[126.9054069,37.4878436],[126.90513464,37.48802089],[126.90491121,37.48823692],[126.90474518,37.48848338],[126.90464295,37.48875081],[126.90460842,37.48902893],[126.90464295,37.48930704],[126.90474518,37.48957447],[126.90491121,37.48982093],[126.90513464,37.49003695],[126.9054069,37.49021424],[126.90571751,37.49034597],[126.90605455,37.4904271],[126.90640505,37.49045449],[126.90675556,37.4904271],[126.9070926,37.49034597],[126.90740321,37.49021424],[126.90767546,37.49003695],[126.9078989,37.48982093],[126.90806492,37.48957447],[126.90816716,37.48930704],[126.90820169,37.48902893]]]}</geom_json>
                <lo_crd>126.906405054451</lo_crd>
                <la_crd>37.489028929143</la_crd>
            </item>
            <item>
                <afos_fid>6516189</afos_fid>
                <afos_id>2019038</afos_id>
                <bjd_cd>1159010900</bjd_cd>
                <spot_cd>11590004</spot_cd>
                <sido_sgg_nm>서울특별시 동작구4</sido_sgg_nm>
                <spot_nm>서울특별시 동작구 신대방동(모스키친 부근)</spot_nm>
                <occrrnc_cnt>4</occrrnc_cnt>
                <caslt_cnt>4</caslt_cnt>
                <dth_dnv_cnt>0</dth_dnv_cnt>
                <se_dnv_cnt>1</se_dnv_cnt>
                <sl_dnv_cnt>2</sl_dnv_cnt>
                <wnd_dnv_cnt>1</wnd_dnv_cnt>
                <geom_json>{"type":"Polygon","coordinates":[[[126.9295586,37.4976016],[126.92952407,37.49732352],[126.92942184,37.49705612],[126.92925581,37.49680968],[126.92903238,37.49659368],[126.92876012,37.49641641],[126.92844951,37.49628468],[126.92811247,37.49620357],[126.92776197,37.49617618],[126.92741146,37.49620357],[126.92707442,37.49628468],[126.92676381,37.49641641],[126.92649156,37.49659368],[126.92626812,37.49680968],[126.9261021,37.49705612],[126.92599986,37.49732352],[126.92596533,37.4976016],[126.92599986,37.49787968],[126.9261021,37.49814708],[126.92626812,37.49839351],[126.92649156,37.49860951],[126.92676381,37.49878677],[126.92707442,37.49891849],[126.92741146,37.49899961],[126.92776197,37.49902699],[126.92811247,37.49899961],[126.92844951,37.49891849],[126.92876012,37.49878677],[126.92903238,37.49860951],[126.92925581,37.49839351],[126.92942184,37.49814708],[126.92952407,37.49787968],[126.9295586,37.4976016]]]}</geom_json>
                <lo_crd>126.927761965543</lo_crd>
                <la_crd>37.497601599635</la_crd>
            </item>
        </items>
        <totalCount>4</totalCount>
        <numOfRows>4</numOfRows>
        <pageNo>1</pageNo>
    </body>
</response>
